{
    "modelo": "RandomForest_Calibrado",
    "version": "1.0",
    "fecha_entrenamiento": "20260520_2231",
    "umbral_decision": 0.5,
    "idx_critico": 0,
    "clases": [
        "Critical",
        "Warning"
    ],
    "n_clases": 2,
    "n_features": 27,
    "features": [
        "Boro (ppm)",
        "Calcio (ppm)",
        "Cinc (ppm)",
        "Fosforado (ppm)",
        "Magnesio (ppm)",
        "Molibdeno (ppm)",
        "Agua (%)",
        "Dilución por combustible (%)",
        "Hollín JOAP (Abs/cm)",
        "Nitración JOAP (Abs/cm)",
        "Oxidación JOAP (Abs/cm)",
        "Silicio (ppm)",
        "Sodio (ppm)",
        "Sulfatación JOAP (Abs/cm)",
        "Viscosidad @ 100°C (cSt)",
        "Aluminio (ppm)",
        "Cobre (ppm)",
        "Cromo (ppm)",
        "Estaño (ppm)",
        "Hierro (ppm)",
        "Plomo (ppm)",
        "SACODE_Salud",
        "SACODE_Desgaste",
        "SACODE_Contaminacion",
        "SACODE_General",
        "Flota",
        "Fault Effect"
    ],
    "cols_numericas": [
        "Boro (ppm)",
        "Calcio (ppm)",
        "Cinc (ppm)",
        "Fosforado (ppm)",
        "Magnesio (ppm)",
        "Molibdeno (ppm)",
        "Agua (%)",
        "Dilución por combustible (%)",
        "Hollín JOAP (Abs/cm)",
        "Nitración JOAP (Abs/cm)",
        "Oxidación JOAP (Abs/cm)",
        "Silicio (ppm)",
        "Sodio (ppm)",
        "Sulfatación JOAP (Abs/cm)",
        "Viscosidad @ 100°C (cSt)",
        "Aluminio (ppm)",
        "Cobre (ppm)",
        "Cromo (ppm)",
        "Estaño (ppm)",
        "Hierro (ppm)",
        "Plomo (ppm)"
    ],
    "cols_sacode": [
        "SACODE_Salud",
        "SACODE_Desgaste",
        "SACODE_Contaminacion",
        "SACODE_General",
        "Flota"
    ],
    "orden_sacode_map": {
        "Normal": 0,
        "Advertencia": 1,
        "Crítico": 2
    },
    "metricas_test": {
        "F1 Weighted (Test)": 0.8472,
        "F1 Crítico (Test)": 0.7,
        "Recall Crítico (Test)": 0.7778,
        "AUC-ROC (Test)": 0.8995,
        "Accuracy (Test)": 0.8421
    },
    "flotas_entrenadas": [
        "Flota_1",
        "Flota_2",
        "Flota_3"
    ],
    "reglas_negocio": [
        "RN-01: No Fault Identified con severidad Warning/Critical → corregido a Normal"
    ]
}